NR_GUI/__init__.py
NR_GUI-0.1.6.dist-info/METADATA
NR_GUI-0.1.6.dist-info/WHEEL
NR_GUI-0.1.6.dist-info/top_level.txt
NR_GUI-0.1.6.dist-info/RECORD
